wa_leg_mcp/__init__.py
wa_leg_mcp/__version__.py
wa_leg_mcp/server.py
wa_leg_mcp/clients/__init__.py
wa_leg_mcp/clients/wsl_client.py
wa_leg_mcp/clients/wsl_search_client.py
wa_leg_mcp/resources/__init__.py
wa_leg_mcp/resources/bill_resources.py
wa_leg_mcp/tools/__init__.py
wa_leg_mcp/tools/bill_tools.py
wa_leg_mcp/tools/committee_tools.py
wa_leg_mcp/tools/legislator_tools.py
wa_leg_mcp/utils/__init__.py
wa_leg_mcp/utils/bill_document_utils.py
wa_leg_mcp/utils/formatters.py
wa_leg_mcp-0.1.0.dist-info/licenses/LICENSE
wa_leg_mcp-0.1.0.dist-info/METADATA
wa_leg_mcp-0.1.0.dist-info/WHEEL
wa_leg_mcp-0.1.0.dist-info/entry_points.txt
wa_leg_mcp-0.1.0.dist-info/top_level.txt
wa_leg_mcp-0.1.0.dist-info/RECORD
