Metadata-Version: 2.4
Name: wa-leg-mcp
Version: 0.1.0
Summary: Model Context Protocol server for Washington State Legislative Web Services API
Author-email: Alex Adacutt <alex@adacutt.house>
License: MIT
Project-URL: Homepage, https://github.com/awalcutt/wa-leg-mcp
Project-URL: Documentation, https://github.com/awalcutt/wa-leg-mcp#readme
Project-URL: Repository, https://github.com/awalcutt/wa-leg-mcp.git
Project-URL: Issues, https://github.com/awalcutt/wa-leg-mcp/issues
Keywords: mcp,washington,legislature,civic,government
Classifier: Development Status :: 3 - Alpha
Classifier: Intended Audience :: Developers
Classifier: License :: OSI Approved :: MIT License
Classifier: Programming Language :: Python :: 3
Classifier: Programming Language :: Python :: 3.10
Classifier: Programming Language :: Python :: 3.11
Classifier: Topic :: Software Development :: Libraries :: Python Modules
Requires-Python: >=3.10
License-File: LICENSE
Requires-Dist: mcp>=1.7.0
Requires-Dist: wa-leg-api>=0.4.0
Requires-Dist: python-dotenv>=1.0.0
Requires-Dist: requests>=2.31.0
Requires-Dist: cachetools>=5.3.0
Requires-Dist: pydantic>=2.0.0
Requires-Dist: typing-extensions>=4.7.0
Provides-Extra: dev
Requires-Dist: pytest>=7.4.0; extra == "dev"
Requires-Dist: pytest-asyncio>=0.21.0; extra == "dev"
Requires-Dist: pytest-cov>=4.1.0; extra == "dev"
Requires-Dist: black>=23.3.0; extra == "dev"
Requires-Dist: ruff>=0.0.280; extra == "dev"
Requires-Dist: isort>=5.12.0; extra == "dev"
Requires-Dist: build>=0.10.0; extra == "dev"
Requires-Dist: twine>=4.0.0; extra == "dev"
Provides-Extra: async
Requires-Dist: aiohttp>=3.8.0; extra == "async"
Provides-Extra: monitoring
Requires-Dist: structlog>=23.1.0; extra == "monitoring"
Provides-Extra: all
Requires-Dist: wa-leg-mcp[async,monitoring]; extra == "all"
Dynamic: license-file
